LICENSE.txt
MANIFEST.in
README.md
setup.py
jupyter_xblock.egg-info/PKG-INFO
jupyter_xblock.egg-info/SOURCES.txt
jupyter_xblock.egg-info/dependency_links.txt
jupyter_xblock.egg-info/entry_points.txt
jupyter_xblock.egg-info/requires.txt
jupyter_xblock.egg-info/top_level.txt
jupyterxblock/__init__.py
jupyterxblock/xblock.py
jupyterxblock/static/css/student.css