Metadata-Version: 2.1
Name: jupyter-xblock
Version: 16.0.0
Summary: Jupyter XBlock for Open edX
Home-page: UNKNOWN
Author: Overhang.IO
Author-email: contact@overhang.io
Maintainer: Overhang.IO
Maintainer-email: regis@overhang.io
License: AGPLv3
Project-URL: Documentation, https://github.com/overhangio/jupyter-xblock
Project-URL: Code, https://github.com/overhangio/jupyter-xblock
Project-URL: Issue tracker, https://github.com/overhangio/jupyter-xblock/issues
Project-URL: Community, https://discuss.openedx.com
Platform: UNKNOWN
Classifier: Development Status :: 5 - Production/Stable
Classifier: Intended Audience :: Developers
Classifier: License :: OSI Approved :: GNU Affero General Public License v3
Classifier: Operating System :: OS Independent
Classifier: Programming Language :: Python
Classifier: Programming Language :: Python :: 3.8
Classifier: Programming Language :: Python :: 3.9
Classifier: Programming Language :: Python :: 3.10
Classifier: Programming Language :: Python :: 3.11
Requires-Python: >=3.8
License-File: LICENSE.txt
